README.rst
eventsocket.py
setup.py
eventsocket.egg-info/PKG-INFO
eventsocket.egg-info/SOURCES.txt
eventsocket.egg-info/dependency_links.txt
eventsocket.egg-info/requires.txt
eventsocket.egg-info/top_level.txt