Metadata-Version: 1.0
Name: eventsocket
Version: 0.1.5
Summary: Twisted protocol for the FreeSWITCH's Event Socket
Home-page: http://github.com/fiorix/eventsocket
Author: Alexandre Fiori
Author-email: UNKNOWN
License: UNKNOWN
Platform: UNKNOWN
